{
    "1":{
        "intro":"kjhgjhghjghjbhvjvgcfcfgcfgcghcjvlhvlhjvghcdgdxgvhbkjblgtgxfcvbçkhvhcgf\njfdfdhsgf \\eesg djdrdtydrr",
        "a":"maurilio",
        "b":"miguel",
        "c":"thais",
        "d":"test",
        "e":"niguem",
        "response":"A"
    },
    "2":{
        "intro":"2",
        "a":"maurilio",
        "b":"miguel",
        "c":"thais",
        "d":"test",
        "e":"niguem",
        "response":"B"
    },
    "3":{
        "intro":"3",
        "a":"maurilio",
        "b":"miguel",
        "c":"thais",
        "d":"test",
        "e":"niguem",
        "response":"C"
    },
    "4":{
        "intro":"4",
        "a":"maurilio",
        "b":"miguel",
        "c":"thais",
        "d":"test",
        "e":"niguem",
        "response":"D"
    },
    "5":{
        "intro":"5",
        "a":"maurilio",
        "b":"miguel",
        "c":"thais",
        "d":"test",
        "e":"niguem",
        "response":"E"
    },
    "6":{
        "intro":"6",
        "a":"maurilio",
        "b":"miguel",
        "c":"thais",
        "d":"test",
        "e":"niguem",
        "response":"E"
    },
    "7":{
        "intro":"7",
        "a":"maurilio",
        "b":"miguel",
        "c":"thais",
        "d":"test",
        "e":"niguem",
        "response":"D"
    },
    "8":{
        "intro":"8",
        "a":"maurilio",
        "b":"miguel",
        "c":"thais",
        "d":"test",
        "e":"niguem",
        "response":"C"
    },
    "9":{
        "intro":"9",
        "a":"maurilio",
        "b":"miguel",
        "c":"thais",
        "d":"test",
        "e":"niguem",
        "response":"B"
    },
    "10":{
        "intro":"10",
        "a":"maurilio",
        "b":"miguel",
        "c":"thais",
        "d":"test",
        "e":"niguem",
        "response":"A"
    }
}